{
	"backtrace" : 0,
	"backtraceGraph" : 
	{
		"commands" : [],
		"files" : 
		[
			"CMakeLists.txt"
		],
		"nodes" : 
		[
			{
				"file" : 0
			}
		]
	},
	"dependencies" : 
	[
		{
			"id" : "Common::@2fb5612c547da95a2da8"
		},
		{
			"id" : "Utilities::@0481113d28085d0ba516"
		},
		{
			"id" : "rtosim_ik_from_file::@145eef247bfb46b6828c"
		},
		{
			"id" : "OutputDevice::@31be673dcad8c7d32ab2"
		},
		{
			"id" : "InverseKinematics::@71dc02479236661ca3cf"
		},
		{
			"id" : "InputDevice::@ef184b226c02836cf020"
		},
		{
			"id" : "rtosim_ik_id_from_file::@145eef247bfb46b6828c"
		},
		{
			"id" : "InverseDynamics::@57ce7b3921e353d17c0f"
		},
		{
			"id" : "SignalProcessing::@67470f21c1e6f00e75d8"
		},
		{
			"id" : "rtosim_id_from_file::@145eef247bfb46b6828c"
		},
		{
			"id" : "testInverseKinematics::@0ed3f7821256f70ed53a"
		},
		{
			"id" : "ZERO_CHECK::@6890427a1f51a3e7e1df"
		}
	],
	"id" : "ALL_BUILD::@6890427a1f51a3e7e1df",
	"isGeneratorProvided" : true,
	"name" : "ALL_BUILD",
	"paths" : 
	{
		"build" : ".",
		"source" : "."
	},
	"sources" : [],
	"type" : "UTILITY"
}
